ipv4tree/__init__.py
ipv4tree/ipv4tree.py
ipv4tree/multiprocessing.py
ipv4tree/utils.py
ipv4tree-0.0.7.dist-info/LICENSE
ipv4tree-0.0.7.dist-info/METADATA
ipv4tree-0.0.7.dist-info/WHEEL
ipv4tree-0.0.7.dist-info/top_level.txt
ipv4tree-0.0.7.dist-info/RECORD
