Metadata-Version: 2.1
Name: ipv4tree
Version: 0.0.7
Summary: IPv4 addresses info data structure
Home-page: https://github.com/dvolkow/ipv4tree
Author: Daniel Wolkow
Author-email: volkov12@rambler.ru
License: GPLv3
Requires-Python: >=3.6
License-File: LICENSE
Requires-Dist: ipaddress
